carconnectivity_connector_volkswagen-0.10.3.dist-info/licenses/LICENSE
carconnectivity_connectors/volkswagen/__init__.py
carconnectivity_connectors/volkswagen/_version.py
carconnectivity_connectors/volkswagen/capability.py
carconnectivity_connectors/volkswagen/charging.py
carconnectivity_connectors/volkswagen/climatization.py
carconnectivity_connectors/volkswagen/command_impl.py
carconnectivity_connectors/volkswagen/connector.py
carconnectivity_connectors/volkswagen/vehicle.py
carconnectivity_connectors/volkswagen/auth/__init__.py
carconnectivity_connectors/volkswagen/auth/auth_util.py
carconnectivity_connectors/volkswagen/auth/openid_session.py
carconnectivity_connectors/volkswagen/auth/session_manager.py
carconnectivity_connectors/volkswagen/auth/vw_web_session.py
carconnectivity_connectors/volkswagen/auth/we_connect_session.py
carconnectivity_connectors/volkswagen/auth/helpers/blacklist_retry.py
carconnectivity_connectors/volkswagen/services/volkswagen_location_service.py
carconnectivity_connectors/volkswagen/ui/connector_ui.py
carconnectivity_connector_volkswagen-0.10.3.dist-info/METADATA
carconnectivity_connector_volkswagen-0.10.3.dist-info/WHEEL
carconnectivity_connector_volkswagen-0.10.3.dist-info/top_level.txt
carconnectivity_connector_volkswagen-0.10.3.dist-info/RECORD
